factorial_minhdeptrai/__init__.py
factorial_minhdeptrai/app.py
factorial_minhdeptrai/factorial.py
factorial_minhdeptrai-0.1.0.dist-info/METADATA
factorial_minhdeptrai-0.1.0.dist-info/WHEEL
factorial_minhdeptrai-0.1.0.dist-info/RECORD
